sds011lib/__init__.py
sds011lib/_constants.py
sds011lib/exceptions.py
sds011lib/py.typed
sds011lib/responses.py
sds011lib-0.4.0.dist-info/LICENSE
sds011lib-0.4.0.dist-info/METADATA
sds011lib-0.4.0.dist-info/WHEEL
sds011lib-0.4.0.dist-info/RECORD
