Metadata-Version: 2.1
Name: sds011lib
Version: 0.4.0
Summary: SDS011 Library
Author: Tim Orme
Author-email: TimothyOrme@gmail.com
Requires-Python: >=3.8,<4.0
Classifier: Programming Language :: Python :: 3
Classifier: Programming Language :: Python :: 3.8
Classifier: Programming Language :: Python :: 3.9
Classifier: Programming Language :: Python :: 3.10
Classifier: Programming Language :: Python :: 3.11
Requires-Dist: pyserial (>=3.5,<4.0)
